{"fastaInput":"e710ca3e2cb3a1f1da7c1c397a57b0db",
"forSelect":"knock-out",
"geneInput":"",
"isIsoform":false,
"opts":["-J","-BED","-GenBank","-G","hg38","-filterGCmin","10","-filterGCmax","90","-rm1perfOff","-t","CODING","-n",
"N","-R","4","-3","PRODUCT_SIZE_MIN=150,PRODUCT_SIZE_MAX=290,PRIMER_MIN_SIZE=18,PRIMER_MAX_SIZE=25,PRIMER_OPT_SIZE=22,PRIMER_MIN_TM=57,PRIMER_MAX_TM=63,PRIMER_OPT_TM=60",
"-P","-A","290","-DF","300","-a","20","-T","1","-g","20","-scoringMethod","DOENCH_2016","-f","NN","-v","3","-repairPredictions","mESC","-M","NGG","-BB","AGGCTAGTCCGT"]}
